CHANGELOG.rst
MANIFEST.in
README.rst
setup.py
slapos/__init__.py
slapos.recipe.template.egg-info/PKG-INFO
slapos.recipe.template.egg-info/SOURCES.txt
slapos.recipe.template.egg-info/dependency_links.txt
slapos.recipe.template.egg-info/entry_points.txt
slapos.recipe.template.egg-info/namespace_packages.txt
slapos.recipe.template.egg-info/requires.txt
slapos.recipe.template.egg-info/top_level.txt
slapos.recipe.template.egg-info/zip-safe
slapos/recipe/__init__.py
slapos/recipe/template/README.jinja2.txt
slapos/recipe/template/README.txt
slapos/recipe/template/__init__.py
slapos/recipe/template/jinja2_template.py
slapos/recipe/template/tests.py