Metadata-Version: 1.1
Name: slapos.recipe.template
Version: 5.0
Summary: Templating recipe with remote resource support.
Home-page: UNKNOWN
Author: UNKNOWN
Author-email: UNKNOWN
License: GPLv3
Keywords: slapos recipe
Platform: UNKNOWN
Classifier: Framework :: Buildout :: Recipe
Classifier: Programming Language :: Python
